<?xml version="1.0" encoding="UTF-8" standalone="no"?>
<!DOCTYPE story SYSTEM "../InScript.dtd">
<story id="095" scenario="grocery">
    <text>
        <content>Sunday , my husband and I did our grocery shopping . 
He had a shopping list recorded in his cell phone . 
We arrived at the store in the early afternoon , and the first thing we did was get a shopping cart . 
We walked in and went to the produce area first , where all the fruit and vegetables are . 
My husband checked the list . 
We only had bananas on the list , but I said we should get things for salad , too , so he picked out bananas and bell peppers while I got lettuce and radishes and tomatoes . 
Then we went to the deli area and ordered some sliced turkey . 
The man behind the counter sliced the turkey for us and measured it on a scale to give us the amount we wanted , then wrapped it up for us . 
Next we visited the bakery area and picked out a nice loaf of rye bread to put the turkey on . 
In the canned goods area , we picked out soup and white beans ; then we went to the pasta area to get pasta and sauce . 
In the meat area , we picked up some chicken breasts and Italian sausage . 
Then we went to the dairy refrigerators and we each picked out some flavors of yogurt we like , and got milk and butter and eggs . 
We were nearly done , so my husband checked the list again and we saw we had forgotten tin foil and toilet paper , so we went back and got those two things . 
Then we went to the check-out where we put all our groceries on a conveyor belt and the clerk scanned each item in an electronic scanner to find out what it cost . 
She told us the total , and I swiped my bank card through an electronic reader to pay . 
Meanwhile , a bagger was putting our groceries into re-usable shopping bags that we had brought with us . 
He put the bags back into the cart . 
We got a receipt from the clerk and pushed the cart out to our car , where we moved the bags into the back seat . 
Then my husband put the cart in little corral in the parking lot that keeps the carts away from people 's cars , and we got in our car and went home . </content>
        <sentences>
            <sentence id="1">
                <token content="Sunday" id="1-1">
                    <pos type="NNP"/>
                    <lemma type="Sunday"/>
                    <dep head="1-7" type="tmod"/>
                </token>
                <token content="," id="1-2"/>
                <token content="my" id="1-3">
                    <pos type="PRP$"/>
                    <lemma type="my"/>
                </token>
                <token content="husband" id="1-4">
                    <pos type="NN"/>
                    <lemma type="husband"/>
                    <dep head="1-7" type="nsubj"/>
                </token>
                <token content="and" id="1-5"/>
                <token content="I" id="1-6">
                    <pos type="PRP"/>
                    <lemma type="I"/>
                </token>
                <token content="did" id="1-7">
                    <pos type="VBD"/>
                    <lemma type="do"/>
                </token>
                <token content="our" id="1-8">
                    <pos type="PRP$"/>
                    <lemma type="we"/>
                </token>
                <token content="grocery" id="1-9">
                    <pos type="NN"/>
                    <lemma type="grocery"/>
                </token>
                <token content="shopping" id="1-10">
                    <pos type="NN"/>
                    <lemma type="shopping"/>
                    <dep head="1-7" type="dobj"/>
                </token>
                <token content="." id="1-11"/>
            </sentence>
            <sentence id="2">
                <token content="He" id="2-1">
                    <pos type="PRP"/>
                    <lemma type="he"/>
                    <dep head="2-2" type="nsubj"/>
                </token>
                <token content="had" id="2-2">
                    <pos type="VBD"/>
                    <lemma type="have"/>
                </token>
                <token content="a" id="2-3">
                    <pos type="DT"/>
                    <lemma type="a"/>
                </token>
                <token content="shopping" id="2-4">
                    <pos type="NN"/>
                    <lemma type="shopping"/>
                </token>
                <token content="list" id="2-5">
                    <pos type="NN"/>
                    <lemma type="list"/>
                    <dep head="2-2" type="dobj"/>
                </token>
                <token content="recorded" id="2-6">
                    <pos type="VBN"/>
                    <lemma type="record"/>
                </token>
                <token content="in" id="2-7"/>
                <token content="his" id="2-8">
                    <pos type="PRP$"/>
                    <lemma type="he"/>
                </token>
                <token content="cell" id="2-9">
                    <pos type="NN"/>
                    <lemma type="cell"/>
                </token>
                <token content="phone" id="2-10">
                    <pos type="NN"/>
                    <lemma type="phone"/>
                    <dep head="2-6" type="prep"/>
                </token>
                <token content="." id="2-11"/>
            </sentence>
            <sentence id="3">
                <token content="We" id="3-1">
                    <pos type="PRP"/>
                    <lemma type="we"/>
                    <dep head="3-2" type="nsubj"/>
                </token>
                <token content="arrived" id="3-2">
                    <pos type="VBD"/>
                    <lemma type="arrive"/>
                </token>
                <token content="at" id="3-3"/>
                <token content="the" id="3-4">
                    <pos type="DT"/>
                    <lemma type="the"/>
                </token>
                <token content="store" id="3-5">
                    <pos type="NN"/>
                    <lemma type="store"/>
                    <dep head="3-2" type="prep"/>
                </token>
                <token content="in" id="3-6"/>
                <token content="the" id="3-7">
                    <pos type="DT"/>
                    <lemma type="the"/>
                </token>
                <token content="early" id="3-8">
                    <pos type="JJ"/>
                    <lemma type="early"/>
                </token>
                <token content="afternoon" id="3-9">
                    <pos type="NN"/>
                    <lemma type="afternoon"/>
                    <dep head="3-2" type="prep"/>
                </token>
                <token content="," id="3-10"/>
                <token content="and" id="3-11"/>
                <token content="the" id="3-12">
                    <pos type="DT"/>
                    <lemma type="the"/>
                </token>
                <token content="first" id="3-13">
                    <pos type="JJ"/>
                    <lemma type="first"/>
                </token>
                <token content="thing" id="3-14">
                    <pos type="NN"/>
                    <lemma type="thing"/>
                    <dep head="3-17" type="nsubj"/>
                </token>
                <token content="we" id="3-15">
                    <pos type="PRP"/>
                    <lemma type="we"/>
                    <dep head="3-16" type="nsubj"/>
                </token>
                <token content="did" id="3-16">
                    <pos type="VBD"/>
                    <lemma type="do"/>
                </token>
                <token content="was" id="3-17">
                    <pos type="VBD"/>
                    <lemma type="be"/>
                    <dep head="3-2" type="conj"/>
                </token>
                <token content="get" id="3-18">
                    <pos type="VB"/>
                    <lemma type="get"/>
                    <dep head="3-17" type="ccomp"/>
                </token>
                <token content="a" id="3-19">
                    <pos type="DT"/>
                    <lemma type="a"/>
                </token>
                <token content="shopping" id="3-20">
                    <pos type="NN"/>
                    <lemma type="shopping"/>
                </token>
                <token content="cart" id="3-21">
                    <pos type="NN"/>
                    <lemma type="cart"/>
                    <dep head="3-18" type="dobj"/>
                </token>
                <token content="." id="3-22"/>
            </sentence>
            <sentence id="4">
                <token content="We" id="4-1">
                    <pos type="PRP"/>
                    <lemma type="we"/>
                    <dep head="4-2" type="nsubj"/>
                </token>
                <token content="walked" id="4-2">
                    <pos type="VBD"/>
                    <lemma type="walk"/>
                </token>
                <token content="in" id="4-3">
                    <pos type="RP"/>
                    <lemma type="in"/>
                    <dep head="4-2" type="prt"/>
                </token>
                <token content="and" id="4-4"/>
                <token content="went" id="4-5">
                    <pos type="VBD"/>
                    <lemma type="go"/>
                    <dep head="4-2" type="conj"/>
                </token>
                <token content="to" id="4-6"/>
                <token content="the" id="4-7">
                    <pos type="DT"/>
                    <lemma type="the"/>
                </token>
                <token content="produce" id="4-8">
                    <pos type="NN"/>
                    <lemma type="produce"/>
                </token>
                <token content="area" id="4-9">
                    <pos type="NN"/>
                    <lemma type="area"/>
                    <dep head="4-5" type="prep"/>
                </token>
                <token content="first" id="4-10">
                    <pos type="RB"/>
                    <lemma type="first"/>
                    <dep head="4-5" type="advmod"/>
                </token>
                <token content="," id="4-11"/>
                <token content="where" id="4-12">
                    <pos type="WRB"/>
                    <lemma type="where"/>
                    <dep head="4-18" type="advmod"/>
                </token>
                <token content="all" id="4-13">
                    <pos type="PDT"/>
                    <lemma type="all"/>
                </token>
                <token content="the" id="4-14">
                    <pos type="DT"/>
                    <lemma type="the"/>
                </token>
                <token content="fruit" id="4-15">
                    <pos type="NN"/>
                    <lemma type="fruit"/>
                    <dep head="4-18" type="nsubj"/>
                </token>
                <token content="and" id="4-16"/>
                <token content="vegetables" id="4-17">
                    <pos type="NNS"/>
                    <lemma type="vegetable"/>
                </token>
                <token content="are" id="4-18">
                    <pos type="VBP"/>
                    <lemma type="be"/>
                    <dep head="4-5" type="advcl"/>
                </token>
                <token content="." id="4-19"/>
            </sentence>
            <sentence id="5">
                <token content="My" id="5-1">
                    <pos type="PRP$"/>
                    <lemma type="my"/>
                </token>
                <token content="husband" id="5-2">
                    <pos type="NN"/>
                    <lemma type="husband"/>
                    <dep head="5-3" type="nsubj"/>
                </token>
                <token content="checked" id="5-3">
                    <pos type="VBD"/>
                    <lemma type="check"/>
                </token>
                <token content="the" id="5-4">
                    <pos type="DT"/>
                    <lemma type="the"/>
                </token>
                <token content="list" id="5-5">
                    <pos type="NN"/>
                    <lemma type="list"/>
                    <dep head="5-3" type="dobj"/>
                </token>
                <token content="." id="5-6"/>
            </sentence>
            <sentence id="6">
                <token content="We" id="6-1">
                    <pos type="PRP"/>
                    <lemma type="we"/>
                    <dep head="6-3" type="nsubj"/>
                </token>
                <token content="only" id="6-2">
                    <pos type="RB"/>
                    <lemma type="only"/>
                    <dep head="6-3" type="advmod"/>
                </token>
                <token content="had" id="6-3">
                    <pos type="VBD"/>
                    <lemma type="have"/>
                </token>
                <token content="bananas" id="6-4">
                    <pos type="NNS"/>
                    <lemma type="banana"/>
                    <dep head="6-3" type="dobj"/>
                </token>
                <token content="on" id="6-5"/>
                <token content="the" id="6-6">
                    <pos type="DT"/>
                    <lemma type="the"/>
                </token>
                <token content="list" id="6-7">
                    <pos type="NN"/>
                    <lemma type="list"/>
                </token>
                <token content="," id="6-8"/>
                <token content="but" id="6-9"/>
                <token content="I" id="6-10">
                    <pos type="PRP"/>
                    <lemma type="I"/>
                    <dep head="6-11" type="nsubj"/>
                </token>
                <token content="said" id="6-11">
                    <pos type="VBD"/>
                    <lemma type="say"/>
                    <dep head="6-3" type="conj"/>
                </token>
                <token content="we" id="6-12">
                    <pos type="PRP"/>
                    <lemma type="we"/>
                    <dep head="6-14" type="nsubj"/>
                </token>
                <token content="should" id="6-13">
                    <pos type="MD"/>
                    <lemma type="should"/>
                    <dep head="6-14" type="aux"/>
                </token>
                <token content="get" id="6-14">
                    <pos type="VB"/>
                    <lemma type="get"/>
                    <dep head="6-11" type="ccomp"/>
                </token>
                <token content="things" id="6-15">
                    <pos type="NNS"/>
                    <lemma type="thing"/>
                    <dep head="6-14" type="dobj"/>
                </token>
                <token content="for" id="6-16"/>
                <token content="salad" id="6-17">
                    <pos type="NN"/>
                    <lemma type="salad"/>
                </token>
                <token content="," id="6-18"/>
                <token content="too" id="6-19">
                    <pos type="RB"/>
                    <lemma type="too"/>
                    <dep head="6-14" type="advmod"/>
                </token>
                <token content="," id="6-20"/>
                <token content="so" id="6-21">
                    <pos type="IN"/>
                    <lemma type="so"/>
                    <dep head="6-23" type="mark"/>
                </token>
                <token content="he" id="6-22">
                    <pos type="PRP"/>
                    <lemma type="he"/>
                    <dep head="6-23" type="nsubj"/>
                </token>
                <token content="picked" id="6-23">
                    <pos type="VBD"/>
                    <lemma type="pick"/>
                    <dep head="6-14" type="advcl"/>
                </token>
                <token content="out" id="6-24">
                    <pos type="RP"/>
                    <lemma type="out"/>
                    <dep head="6-23" type="prt"/>
                </token>
                <token content="bananas" id="6-25">
                    <pos type="NNS"/>
                    <lemma type="banana"/>
                    <dep head="6-23" type="dobj"/>
                </token>
                <token content="and" id="6-26"/>
                <token content="bell" id="6-27">
                    <pos type="NN"/>
                    <lemma type="bell"/>
                </token>
                <token content="peppers" id="6-28">
                    <pos type="NNS"/>
                    <lemma type="pepper"/>
                </token>
                <token content="while" id="6-29">
                    <pos type="IN"/>
                    <lemma type="while"/>
                    <dep head="6-31" type="mark"/>
                </token>
                <token content="I" id="6-30">
                    <pos type="PRP"/>
                    <lemma type="I"/>
                    <dep head="6-31" type="nsubj"/>
                </token>
                <token content="got" id="6-31">
                    <pos type="VBD"/>
                    <lemma type="get"/>
                    <dep head="6-23" type="advcl"/>
                </token>
                <token content="lettuce" id="6-32">
                    <pos type="NN"/>
                    <lemma type="lettuce"/>
                    <dep head="6-31" type="dobj"/>
                </token>
                <token content="and" id="6-33"/>
                <token content="radishes" id="6-34">
                    <pos type="NNS"/>
                    <lemma type="radish"/>
                </token>
                <token content="and" id="6-35"/>
                <token content="tomatoes" id="6-36">
                    <pos type="NNS"/>
                    <lemma type="tomato"/>
                </token>
                <token content="." id="6-37"/>
            </sentence>
            <sentence id="7">
                <token content="Then" id="7-1">
                    <pos type="RB"/>
                    <lemma type="then"/>
                    <dep head="7-3" type="advmod"/>
                </token>
                <token content="we" id="7-2">
                    <pos type="PRP"/>
                    <lemma type="we"/>
                    <dep head="7-3" type="nsubj"/>
                </token>
                <token content="went" id="7-3">
                    <pos type="VBD"/>
                    <lemma type="go"/>
                </token>
                <token content="to" id="7-4"/>
                <token content="the" id="7-5">
                    <pos type="DT"/>
                    <lemma type="the"/>
                </token>
                <token content="deli" id="7-6">
                    <pos type="NNS"/>
                    <lemma type="deli"/>
                </token>
                <token content="area" id="7-7">
                    <pos type="NN"/>
                    <lemma type="area"/>
                    <dep head="7-3" type="prep"/>
                </token>
                <token content="and" id="7-8"/>
                <token content="ordered" id="7-9">
                    <pos type="VBD"/>
                    <lemma type="order"/>
                    <dep head="7-3" type="conj"/>
                </token>
                <token content="some" id="7-10">
                    <pos type="DT"/>
                    <lemma type="some"/>
                </token>
                <token content="sliced" id="7-11">
                    <pos type="JJ"/>
                    <lemma type="sliced"/>
                </token>
                <token content="turkey" id="7-12">
                    <pos type="NN"/>
                    <lemma type="turkey"/>
                    <dep head="7-9" type="dobj"/>
                </token>
                <token content="." id="7-13"/>
            </sentence>
            <sentence id="8">
                <token content="The" id="8-1">
                    <pos type="DT"/>
                    <lemma type="the"/>
                </token>
                <token content="man" id="8-2">
                    <pos type="NN"/>
                    <lemma type="man"/>
                    <dep head="8-6" type="nsubj"/>
                </token>
                <token content="behind" id="8-3"/>
                <token content="the" id="8-4">
                    <pos type="DT"/>
                    <lemma type="the"/>
                </token>
                <token content="counter" id="8-5">
                    <pos type="NN"/>
                    <lemma type="counter"/>
                </token>
                <token content="sliced" id="8-6">
                    <pos type="VBD"/>
                    <lemma type="slice"/>
                </token>
                <token content="the" id="8-7">
                    <pos type="DT"/>
                    <lemma type="the"/>
                </token>
                <token content="turkey" id="8-8">
                    <pos type="NN"/>
                    <lemma type="turkey"/>
                    <dep head="8-6" type="dobj"/>
                </token>
                <token content="for" id="8-9"/>
                <token content="us" id="8-10">
                    <pos type="PRP"/>
                    <lemma type="we"/>
                    <dep head="8-6" type="prep"/>
                </token>
                <token content="and" id="8-11"/>
                <token content="measured" id="8-12">
                    <pos type="VBD"/>
                    <lemma type="measure"/>
                    <dep head="8-6" type="conj"/>
                </token>
                <token content="it" id="8-13">
                    <pos type="PRP"/>
                    <lemma type="it"/>
                    <dep head="8-12" type="dobj"/>
                </token>
                <token content="on" id="8-14"/>
                <token content="a" id="8-15">
                    <pos type="DT"/>
                    <lemma type="a"/>
                </token>
                <token content="scale" id="8-16">
                    <pos type="NN"/>
                    <lemma type="scale"/>
                    <dep head="8-12" type="prep"/>
                </token>
                <token content="to" id="8-17">
                    <pos type="TO"/>
                    <lemma type="to"/>
                    <dep head="8-18" type="aux"/>
                </token>
                <token content="give" id="8-18">
                    <pos type="VB"/>
                    <lemma type="give"/>
                </token>
                <token content="us" id="8-19">
                    <pos type="PRP"/>
                    <lemma type="we"/>
                    <dep head="8-18" type="iobj"/>
                </token>
                <token content="the" id="8-20">
                    <pos type="DT"/>
                    <lemma type="the"/>
                </token>
                <token content="amount" id="8-21">
                    <pos type="NN"/>
                    <lemma type="amount"/>
                    <dep head="8-18" type="dobj"/>
                </token>
                <token content="we" id="8-22">
                    <pos type="PRP"/>
                    <lemma type="we"/>
                    <dep head="8-23" type="nsubj"/>
                </token>
                <token content="wanted" id="8-23">
                    <pos type="VBD"/>
                    <lemma type="want"/>
                </token>
                <token content="," id="8-24"/>
                <token content="then" id="8-25">
                    <pos type="RB"/>
                    <lemma type="then"/>
                    <dep head="8-26" type="advmod"/>
                </token>
                <token content="wrapped" id="8-26">
                    <pos type="VBD"/>
                    <lemma type="wrap"/>
                    <dep head="8-6" type="dep"/>
                </token>
                <token content="it" id="8-27">
                    <pos type="PRP"/>
                    <lemma type="it"/>
                    <dep head="8-26" type="dobj"/>
                </token>
                <token content="up" id="8-28">
                    <pos type="RP"/>
                    <lemma type="up"/>
                    <dep head="8-26" type="prt"/>
                </token>
                <token content="for" id="8-29"/>
                <token content="us" id="8-30">
                    <pos type="PRP"/>
                    <lemma type="we"/>
                    <dep head="8-26" type="prep"/>
                </token>
                <token content="." id="8-31"/>
            </sentence>
            <sentence id="9">
                <token content="Next" id="9-1">
                    <pos type="RB"/>
                    <lemma type="next"/>
                    <dep head="9-3" type="advmod"/>
                </token>
                <token content="we" id="9-2">
                    <pos type="PRP"/>
                    <lemma type="we"/>
                    <dep head="9-3" type="nsubj"/>
                </token>
                <token content="visited" id="9-3">
                    <pos type="VBD"/>
                    <lemma type="visit"/>
                </token>
                <token content="the" id="9-4">
                    <pos type="DT"/>
                    <lemma type="the"/>
                </token>
                <token content="bakery" id="9-5">
                    <pos type="NN"/>
                    <lemma type="bakery"/>
                </token>
                <token content="area" id="9-6">
                    <pos type="NN"/>
                    <lemma type="area"/>
                    <dep head="9-3" type="dobj"/>
                </token>
                <token content="and" id="9-7"/>
                <token content="picked" id="9-8">
                    <pos type="VBD"/>
                    <lemma type="pick"/>
                    <dep head="9-3" type="conj"/>
                </token>
                <token content="out" id="9-9">
                    <pos type="RP"/>
                    <lemma type="out"/>
                    <dep head="9-8" type="prt"/>
                </token>
                <token content="a" id="9-10">
                    <pos type="DT"/>
                    <lemma type="a"/>
                </token>
                <token content="nice" id="9-11">
                    <pos type="JJ"/>
                    <lemma type="nice"/>
                </token>
                <token content="loaf" id="9-12">
                    <pos type="NN"/>
                    <lemma type="loaf"/>
                    <dep head="9-8" type="dobj"/>
                </token>
                <token content="of" id="9-13"/>
                <token content="rye" id="9-14">
                    <pos type="NN"/>
                    <lemma type="rye"/>
                </token>
                <token content="bread" id="9-15">
                    <pos type="NN"/>
                    <lemma type="bread"/>
                </token>
                <token content="to" id="9-16">
                    <pos type="TO"/>
                    <lemma type="to"/>
                    <dep head="9-17" type="aux"/>
                </token>
                <token content="put" id="9-17">
                    <pos type="VB"/>
                    <lemma type="put"/>
                    <dep head="9-3" type="xcomp"/>
                </token>
                <token content="the" id="9-18">
                    <pos type="DT"/>
                    <lemma type="the"/>
                </token>
                <token content="turkey" id="9-19">
                    <pos type="NN"/>
                    <lemma type="turkey"/>
                    <dep head="9-17" type="dobj"/>
                </token>
                <token content="on" id="9-20">
                    <pos type="RP"/>
                    <lemma type="on"/>
                    <dep head="9-17" type="prt"/>
                </token>
                <token content="." id="9-21"/>
            </sentence>
            <sentence id="10">
                <token content="In" id="10-1"/>
                <token content="the" id="10-2">
                    <pos type="DT"/>
                    <lemma type="the"/>
                </token>
                <token content="canned" id="10-3">
                    <pos type="VBN"/>
                    <lemma type="can"/>
                </token>
                <token content="goods" id="10-4">
                    <pos type="NNS"/>
                    <lemma type="goods"/>
                </token>
                <token content="area" id="10-5">
                    <pos type="NN"/>
                    <lemma type="area"/>
                    <dep head="10-8" type="prep"/>
                </token>
                <token content="," id="10-6"/>
                <token content="we" id="10-7">
                    <pos type="PRP"/>
                    <lemma type="we"/>
                    <dep head="10-8" type="nsubj"/>
                </token>
                <token content="picked" id="10-8">
                    <pos type="VBD"/>
                    <lemma type="pick"/>
                </token>
                <token content="out" id="10-9">
                    <pos type="RP"/>
                    <lemma type="out"/>
                    <dep head="10-8" type="prt"/>
                </token>
                <token content="soup" id="10-10">
                    <pos type="NN"/>
                    <lemma type="soup"/>
                    <dep head="10-8" type="dobj"/>
                </token>
                <token content="and" id="10-11"/>
                <token content="white" id="10-12">
                    <pos type="JJ"/>
                    <lemma type="white"/>
                </token>
                <token content="beans" id="10-13">
                    <pos type="NNS"/>
                    <lemma type="bean"/>
                </token>
                <token content=";" id="10-14"/>
                <token content="then" id="10-15">
                    <pos type="RB"/>
                    <lemma type="then"/>
                    <dep head="10-17" type="advmod"/>
                </token>
                <token content="we" id="10-16">
                    <pos type="PRP"/>
                    <lemma type="we"/>
                    <dep head="10-17" type="nsubj"/>
                </token>
                <token content="went" id="10-17">
                    <pos type="VBD"/>
                    <lemma type="go"/>
                    <dep head="10-8" type="parataxis"/>
                </token>
                <token content="to" id="10-18"/>
                <token content="the" id="10-19">
                    <pos type="DT"/>
                    <lemma type="the"/>
                </token>
                <token content="pasta" id="10-20">
                    <pos type="NN"/>
                    <lemma type="pasta"/>
                </token>
                <token content="area" id="10-21">
                    <pos type="NN"/>
                    <lemma type="area"/>
                    <dep head="10-17" type="prep"/>
                </token>
                <token content="to" id="10-22">
                    <pos type="TO"/>
                    <lemma type="to"/>
                    <dep head="10-23" type="aux"/>
                </token>
                <token content="get" id="10-23">
                    <pos type="VB"/>
                    <lemma type="get"/>
                    <dep head="10-17" type="xcomp"/>
                </token>
                <token content="pasta" id="10-24">
                    <pos type="NN"/>
                    <lemma type="pasta"/>
                    <dep head="10-23" type="dobj"/>
                </token>
                <token content="and" id="10-25"/>
                <token content="sauce" id="10-26">
                    <pos type="NN"/>
                    <lemma type="sauce"/>
                </token>
                <token content="." id="10-27"/>
            </sentence>
            <sentence id="11">
                <token content="In" id="11-1"/>
                <token content="the" id="11-2">
                    <pos type="DT"/>
                    <lemma type="the"/>
                </token>
                <token content="meat" id="11-3">
                    <pos type="NN"/>
                    <lemma type="meat"/>
                </token>
                <token content="area" id="11-4">
                    <pos type="NN"/>
                    <lemma type="area"/>
                    <dep head="11-7" type="prep"/>
                </token>
                <token content="," id="11-5"/>
                <token content="we" id="11-6">
                    <pos type="PRP"/>
                    <lemma type="we"/>
                    <dep head="11-7" type="nsubj"/>
                </token>
                <token content="picked" id="11-7">
                    <pos type="VBD"/>
                    <lemma type="pick"/>
                </token>
                <token content="up" id="11-8">
                    <pos type="RP"/>
                    <lemma type="up"/>
                    <dep head="11-7" type="prt"/>
                </token>
                <token content="some" id="11-9">
                    <pos type="DT"/>
                    <lemma type="some"/>
                </token>
                <token content="chicken" id="11-10">
                    <pos type="NN"/>
                    <lemma type="chicken"/>
                </token>
                <token content="breasts" id="11-11">
                    <pos type="NNS"/>
                    <lemma type="breast"/>
                    <dep head="11-7" type="dobj"/>
                </token>
                <token content="and" id="11-12"/>
                <token content="Italian" id="11-13">
                    <pos type="JJ"/>
                    <lemma type="italian"/>
                </token>
                <token content="sausage" id="11-14">
                    <pos type="NN"/>
                    <lemma type="sausage"/>
                </token>
                <token content="." id="11-15"/>
            </sentence>
            <sentence id="12">
                <token content="Then" id="12-1">
                    <pos type="RB"/>
                    <lemma type="then"/>
                    <dep head="12-3" type="advmod"/>
                </token>
                <token content="we" id="12-2">
                    <pos type="PRP"/>
                    <lemma type="we"/>
                    <dep head="12-3" type="nsubj"/>
                </token>
                <token content="went" id="12-3">
                    <pos type="VBD"/>
                    <lemma type="go"/>
                </token>
                <token content="to" id="12-4"/>
                <token content="the" id="12-5">
                    <pos type="DT"/>
                    <lemma type="the"/>
                </token>
                <token content="dairy" id="12-6">
                    <pos type="NN"/>
                    <lemma type="dairy"/>
                </token>
                <token content="refrigerators" id="12-7">
                    <pos type="NNS"/>
                    <lemma type="refrigerator"/>
                    <dep head="12-3" type="prep"/>
                </token>
                <token content="and" id="12-8"/>
                <token content="we" id="12-9">
                    <pos type="PRP"/>
                    <lemma type="we"/>
                    <dep head="12-11" type="nsubj"/>
                </token>
                <token content="each" id="12-10">
                    <pos type="DT"/>
                    <lemma type="each"/>
                    <dep head="12-11" type="advmod"/>
                </token>
                <token content="picked" id="12-11">
                    <pos type="VBD"/>
                    <lemma type="pick"/>
                    <dep head="12-3" type="conj"/>
                </token>
                <token content="out" id="12-12">
                    <pos type="RP"/>
                    <lemma type="out"/>
                    <dep head="12-11" type="prt"/>
                </token>
                <token content="some" id="12-13">
                    <pos type="DT"/>
                    <lemma type="some"/>
                </token>
                <token content="flavors" id="12-14">
                    <pos type="NNS"/>
                    <lemma type="flavor"/>
                    <dep head="12-11" type="dobj"/>
                </token>
                <token content="of" id="12-15"/>
                <token content="yogurt" id="12-16">
                    <pos type="NN"/>
                    <lemma type="yogurt"/>
                </token>
                <token content="we" id="12-17">
                    <pos type="PRP"/>
                    <lemma type="we"/>
                    <dep head="12-18" type="nsubj"/>
                </token>
                <token content="like" id="12-18">
                    <pos type="VBP"/>
                    <lemma type="like"/>
                </token>
                <token content="," id="12-19"/>
                <token content="and" id="12-20"/>
                <token content="got" id="12-21">
                    <pos type="VBD"/>
                    <lemma type="get"/>
                    <dep head="12-18" type="conj"/>
                </token>
                <token content="milk" id="12-22">
                    <pos type="NN"/>
                    <lemma type="milk"/>
                    <dep head="12-21" type="dobj"/>
                </token>
                <token content="and" id="12-23"/>
                <token content="butter" id="12-24">
                    <pos type="NN"/>
                    <lemma type="butter"/>
                </token>
                <token content="and" id="12-25"/>
                <token content="eggs" id="12-26">
                    <pos type="NNS"/>
                    <lemma type="egg"/>
                </token>
                <token content="." id="12-27"/>
            </sentence>
            <sentence id="13">
                <token content="We" id="13-1">
                    <pos type="PRP"/>
                    <lemma type="we"/>
                    <dep head="13-4" type="nsubjpass"/>
                </token>
                <token content="were" id="13-2">
                    <pos type="VBD"/>
                    <lemma type="be"/>
                    <dep head="13-4" type="auxpass"/>
                </token>
                <token content="nearly" id="13-3">
                    <pos type="RB"/>
                    <lemma type="nearly"/>
                    <dep head="13-4" type="advmod"/>
                </token>
                <token content="done" id="13-4">
                    <pos type="VBN"/>
                    <lemma type="do"/>
                </token>
                <token content="," id="13-5"/>
                <token content="so" id="13-6">
                    <pos type="IN"/>
                    <lemma type="so"/>
                    <dep head="13-4" type="dep"/>
                </token>
                <token content="my" id="13-7">
                    <pos type="PRP$"/>
                    <lemma type="my"/>
                </token>
                <token content="husband" id="13-8">
                    <pos type="NN"/>
                    <lemma type="husband"/>
                    <dep head="13-9" type="nsubj"/>
                </token>
                <token content="checked" id="13-9">
                    <pos type="VBD"/>
                    <lemma type="check"/>
                    <dep head="13-4" type="dep"/>
                </token>
                <token content="the" id="13-10">
                    <pos type="DT"/>
                    <lemma type="the"/>
                </token>
                <token content="list" id="13-11">
                    <pos type="NN"/>
                    <lemma type="list"/>
                    <dep head="13-9" type="dobj"/>
                </token>
                <token content="again" id="13-12">
                    <pos type="RB"/>
                    <lemma type="again"/>
                    <dep head="13-9" type="advmod"/>
                </token>
                <token content="and" id="13-13"/>
                <token content="we" id="13-14">
                    <pos type="PRP"/>
                    <lemma type="we"/>
                    <dep head="13-15" type="nsubj"/>
                </token>
                <token content="saw" id="13-15">
                    <pos type="VBD"/>
                    <lemma type="see"/>
                    <dep head="13-4" type="conj"/>
                </token>
                <token content="we" id="13-16">
                    <pos type="PRP"/>
                    <lemma type="we"/>
                    <dep head="13-18" type="nsubj"/>
                </token>
                <token content="had" id="13-17">
                    <pos type="VBD"/>
                    <lemma type="have"/>
                    <dep head="13-18" type="aux"/>
                </token>
                <token content="forgotten" id="13-18">
                    <pos type="VBN"/>
                    <lemma type="forget"/>
                    <dep head="13-15" type="ccomp"/>
                </token>
                <token content="tin" id="13-19">
                    <pos type="NN"/>
                    <lemma type="tin"/>
                </token>
                <token content="foil" id="13-20">
                    <pos type="NN"/>
                    <lemma type="foil"/>
                    <dep head="13-18" type="dobj"/>
                </token>
                <token content="and" id="13-21"/>
                <token content="toilet" id="13-22">
                    <pos type="NN"/>
                    <lemma type="toilet"/>
                </token>
                <token content="paper" id="13-23">
                    <pos type="NN"/>
                    <lemma type="paper"/>
                </token>
                <token content="," id="13-24"/>
                <token content="so" id="13-25">
                    <pos type="IN"/>
                    <lemma type="so"/>
                    <dep head="13-27" type="mark"/>
                </token>
                <token content="we" id="13-26">
                    <pos type="PRP"/>
                    <lemma type="we"/>
                    <dep head="13-27" type="nsubj"/>
                </token>
                <token content="went" id="13-27">
                    <pos type="VBD"/>
                    <lemma type="go"/>
                </token>
                <token content="back" id="13-28">
                    <pos type="RB"/>
                    <lemma type="back"/>
                    <dep head="13-27" type="advmod"/>
                </token>
                <token content="and" id="13-29"/>
                <token content="got" id="13-30">
                    <pos type="VBD"/>
                    <lemma type="get"/>
                    <dep head="13-27" type="conj"/>
                </token>
                <token content="those" id="13-31">
                    <pos type="DT"/>
                    <lemma type="those"/>
                </token>
                <token content="two" id="13-32">
                    <pos type="CD"/>
                    <lemma type="two"/>
                </token>
                <token content="things" id="13-33">
                    <pos type="NNS"/>
                    <lemma type="thing"/>
                    <dep head="13-30" type="dobj"/>
                </token>
                <token content="." id="13-34"/>
            </sentence>
            <sentence id="14">
                <token content="Then" id="14-1">
                    <pos type="RB"/>
                    <lemma type="then"/>
                    <dep head="14-3" type="advmod"/>
                </token>
                <token content="we" id="14-2">
                    <pos type="PRP"/>
                    <lemma type="we"/>
                    <dep head="14-3" type="nsubj"/>
                </token>
                <token content="went" id="14-3">
                    <pos type="VBD"/>
                    <lemma type="go"/>
                </token>
                <token content="to" id="14-4"/>
                <token content="the" id="14-5">
                    <pos type="DT"/>
                    <lemma type="the"/>
                </token>
                <token content="check-out" id="14-6">
                    <pos type="NN"/>
                    <lemma type="check-out"/>
                    <dep head="14-3" type="prep"/>
                </token>
                <token content="where" id="14-7">
                    <pos type="WRB"/>
                    <lemma type="where"/>
                    <dep head="14-9" type="advmod"/>
                </token>
                <token content="we" id="14-8">
                    <pos type="PRP"/>
                    <lemma type="we"/>
                    <dep head="14-9" type="nsubj"/>
                </token>
                <token content="put" id="14-9">
                    <pos type="VBD"/>
                    <lemma type="put"/>
                    <dep head="14-3" type="advcl"/>
                </token>
                <token content="all" id="14-10">
                    <pos type="PDT"/>
                    <lemma type="all"/>
                </token>
                <token content="our" id="14-11">
                    <pos type="PRP$"/>
                    <lemma type="we"/>
                </token>
                <token content="groceries" id="14-12">
                    <pos type="NNS"/>
                    <lemma type="grocery"/>
                    <dep head="14-9" type="dobj"/>
                </token>
                <token content="on" id="14-13"/>
                <token content="a" id="14-14">
                    <pos type="DT"/>
                    <lemma type="a"/>
                </token>
                <token content="conveyor" id="14-15">
                    <pos type="NN"/>
                    <lemma type="conveyor"/>
                </token>
                <token content="belt" id="14-16">
                    <pos type="NN"/>
                    <lemma type="belt"/>
                    <dep head="14-9" type="prep"/>
                </token>
                <token content="and" id="14-17"/>
                <token content="the" id="14-18">
                    <pos type="DT"/>
                    <lemma type="the"/>
                </token>
                <token content="clerk" id="14-19">
                    <pos type="NN"/>
                    <lemma type="clerk"/>
                    <dep head="14-20" type="nsubj"/>
                </token>
                <token content="scanned" id="14-20">
                    <pos type="VBD"/>
                    <lemma type="scan"/>
                    <dep head="14-9" type="conj"/>
                </token>
                <token content="each" id="14-21">
                    <pos type="DT"/>
                    <lemma type="each"/>
                </token>
                <token content="item" id="14-22">
                    <pos type="NN"/>
                    <lemma type="item"/>
                    <dep head="14-20" type="dobj"/>
                </token>
                <token content="in" id="14-23"/>
                <token content="an" id="14-24">
                    <pos type="DT"/>
                    <lemma type="a"/>
                </token>
                <token content="electronic" id="14-25">
                    <pos type="JJ"/>
                    <lemma type="electronic"/>
                </token>
                <token content="scanner" id="14-26">
                    <pos type="NN"/>
                    <lemma type="scanner"/>
                    <dep head="14-20" type="prep"/>
                </token>
                <token content="to" id="14-27">
                    <pos type="TO"/>
                    <lemma type="to"/>
                    <dep head="14-28" type="aux"/>
                </token>
                <token content="find" id="14-28">
                    <pos type="VB"/>
                    <lemma type="find"/>
                    <dep head="14-20" type="vmod"/>
                </token>
                <token content="out" id="14-29">
                    <pos type="RP"/>
                    <lemma type="out"/>
                    <dep head="14-28" type="prt"/>
                </token>
                <token content="what" id="14-30">
                    <pos type="WP"/>
                    <lemma type="what"/>
                    <dep head="14-32" type="dobj"/>
                </token>
                <token content="it" id="14-31">
                    <pos type="PRP"/>
                    <lemma type="it"/>
                    <dep head="14-32" type="nsubj"/>
                </token>
                <token content="cost" id="14-32">
                    <pos type="VBD"/>
                    <lemma type="cost"/>
                    <dep head="14-28" type="ccomp"/>
                </token>
                <token content="." id="14-33"/>
            </sentence>
            <sentence id="15">
                <token content="She" id="15-1">
                    <pos type="PRP"/>
                    <lemma type="she"/>
                    <dep head="15-2" type="nsubj"/>
                </token>
                <token content="told" id="15-2">
                    <pos type="VBD"/>
                    <lemma type="tell"/>
                </token>
                <token content="us" id="15-3">
                    <pos type="PRP"/>
                    <lemma type="we"/>
                </token>
                <token content="the" id="15-4">
                    <pos type="DT"/>
                    <lemma type="the"/>
                </token>
                <token content="total" id="15-5">
                    <pos type="NN"/>
                    <lemma type="total"/>
                    <dep head="15-2" type="xcomp"/>
                </token>
                <token content="," id="15-6"/>
                <token content="and" id="15-7"/>
                <token content="I" id="15-8">
                    <pos type="PRP"/>
                    <lemma type="I"/>
                    <dep head="15-9" type="nsubj"/>
                </token>
                <token content="swiped" id="15-9">
                    <pos type="VBD"/>
                    <lemma type="swipe"/>
                    <dep head="15-2" type="conj"/>
                </token>
                <token content="my" id="15-10">
                    <pos type="PRP$"/>
                    <lemma type="my"/>
                </token>
                <token content="bank" id="15-11">
                    <pos type="NN"/>
                    <lemma type="bank"/>
                </token>
                <token content="card" id="15-12">
                    <pos type="NN"/>
                    <lemma type="card"/>
                    <dep head="15-9" type="dobj"/>
                </token>
                <token content="through" id="15-13"/>
                <token content="an" id="15-14">
                    <pos type="DT"/>
                    <lemma type="a"/>
                </token>
                <token content="electronic" id="15-15">
                    <pos type="JJ"/>
                    <lemma type="electronic"/>
                </token>
                <token content="reader" id="15-16">
                    <pos type="NN"/>
                    <lemma type="reader"/>
                    <dep head="15-9" type="prep"/>
                </token>
                <token content="to" id="15-17">
                    <pos type="TO"/>
                    <lemma type="to"/>
                    <dep head="15-18" type="aux"/>
                </token>
                <token content="pay" id="15-18">
                    <pos type="VB"/>
                    <lemma type="pay"/>
                    <dep head="15-9" type="vmod"/>
                </token>
                <token content="." id="15-19"/>
            </sentence>
            <sentence id="16">
                <token content="Meanwhile" id="16-1">
                    <pos type="RB"/>
                    <lemma type="meanwhile"/>
                    <dep head="16-6" type="advmod"/>
                </token>
                <token content="," id="16-2"/>
                <token content="a" id="16-3">
                    <pos type="DT"/>
                    <lemma type="a"/>
                </token>
                <token content="bagger" id="16-4">
                    <pos type="NN"/>
                    <lemma type="bagger"/>
                    <dep head="16-6" type="nsubj"/>
                </token>
                <token content="was" id="16-5">
                    <pos type="VBD"/>
                    <lemma type="be"/>
                    <dep head="16-6" type="aux"/>
                </token>
                <token content="putting" id="16-6">
                    <pos type="VBG"/>
                    <lemma type="put"/>
                </token>
                <token content="our" id="16-7">
                    <pos type="PRP$"/>
                    <lemma type="we"/>
                </token>
                <token content="groceries" id="16-8">
                    <pos type="NNS"/>
                    <lemma type="grocery"/>
                    <dep head="16-6" type="dobj"/>
                </token>
                <token content="into" id="16-9"/>
                <token content="re-usable" id="16-10">
                    <pos type="JJ"/>
                    <lemma type="re-usable"/>
                </token>
                <token content="shopping" id="16-11">
                    <pos type="NN"/>
                    <lemma type="shopping"/>
                </token>
                <token content="bags" id="16-12">
                    <pos type="NNS"/>
                    <lemma type="bag"/>
                    <dep head="16-6" type="prep"/>
                </token>
                <token content="that" id="16-13">
                    <pos type="IN"/>
                    <lemma type="that"/>
                    <dep head="16-16" type="mark"/>
                </token>
                <token content="we" id="16-14">
                    <pos type="PRP"/>
                    <lemma type="we"/>
                    <dep head="16-16" type="nsubj"/>
                </token>
                <token content="had" id="16-15">
                    <pos type="VBD"/>
                    <lemma type="have"/>
                    <dep head="16-16" type="aux"/>
                </token>
                <token content="brought" id="16-16">
                    <pos type="VBN"/>
                    <lemma type="bring"/>
                    <dep head="16-6" type="ccomp"/>
                </token>
                <token content="with" id="16-17"/>
                <token content="us" id="16-18">
                    <pos type="PRP"/>
                    <lemma type="we"/>
                    <dep head="16-16" type="prep"/>
                </token>
                <token content="." id="16-19"/>
            </sentence>
            <sentence id="17">
                <token content="He" id="17-1">
                    <pos type="PRP"/>
                    <lemma type="he"/>
                    <dep head="17-2" type="nsubj"/>
                </token>
                <token content="put" id="17-2">
                    <pos type="VBD"/>
                    <lemma type="put"/>
                </token>
                <token content="the" id="17-3">
                    <pos type="DT"/>
                    <lemma type="the"/>
                </token>
                <token content="bags" id="17-4">
                    <pos type="NNS"/>
                    <lemma type="bag"/>
                    <dep head="17-2" type="dobj"/>
                </token>
                <token content="back" id="17-5">
                    <pos type="RB"/>
                    <lemma type="back"/>
                    <dep head="17-2" type="advmod"/>
                </token>
                <token content="into" id="17-6"/>
                <token content="the" id="17-7">
                    <pos type="DT"/>
                    <lemma type="the"/>
                </token>
                <token content="cart" id="17-8">
                    <pos type="NN"/>
                    <lemma type="cart"/>
                    <dep head="17-2" type="prep"/>
                </token>
                <token content="." id="17-9"/>
            </sentence>
            <sentence id="18">
                <token content="We" id="18-1">
                    <pos type="PRP"/>
                    <lemma type="we"/>
                    <dep head="18-2" type="nsubj"/>
                </token>
                <token content="got" id="18-2">
                    <pos type="VBD"/>
                    <lemma type="get"/>
                </token>
                <token content="a" id="18-3">
                    <pos type="DT"/>
                    <lemma type="a"/>
                </token>
                <token content="receipt" id="18-4">
                    <pos type="NN"/>
                    <lemma type="receipt"/>
                    <dep head="18-2" type="dobj"/>
                </token>
                <token content="from" id="18-5"/>
                <token content="the" id="18-6">
                    <pos type="DT"/>
                    <lemma type="the"/>
                </token>
                <token content="clerk" id="18-7">
                    <pos type="NN"/>
                    <lemma type="clerk"/>
                    <dep head="18-2" type="prep"/>
                </token>
                <token content="and" id="18-8"/>
                <token content="pushed" id="18-9">
                    <pos type="VBD"/>
                    <lemma type="push"/>
                    <dep head="18-2" type="conj"/>
                </token>
                <token content="the" id="18-10">
                    <pos type="DT"/>
                    <lemma type="the"/>
                </token>
                <token content="cart" id="18-11">
                    <pos type="NN"/>
                    <lemma type="cart"/>
                    <dep head="18-9" type="dobj"/>
                </token>
                <token content="out" id="18-12">
                    <pos type="RP"/>
                    <lemma type="out"/>
                    <dep head="18-9" type="prt"/>
                </token>
                <token content="to" id="18-13"/>
                <token content="our" id="18-14">
                    <pos type="PRP$"/>
                    <lemma type="we"/>
                </token>
                <token content="car" id="18-15">
                    <pos type="NN"/>
                    <lemma type="car"/>
                    <dep head="18-9" type="prep"/>
                </token>
                <token content="," id="18-16"/>
                <token content="where" id="18-17">
                    <pos type="WRB"/>
                    <lemma type="where"/>
                    <dep head="18-19" type="advmod"/>
                </token>
                <token content="we" id="18-18">
                    <pos type="PRP"/>
                    <lemma type="we"/>
                    <dep head="18-19" type="nsubj"/>
                </token>
                <token content="moved" id="18-19">
                    <pos type="VBD"/>
                    <lemma type="move"/>
                </token>
                <token content="the" id="18-20">
                    <pos type="DT"/>
                    <lemma type="the"/>
                </token>
                <token content="bags" id="18-21">
                    <pos type="NNS"/>
                    <lemma type="bag"/>
                    <dep head="18-19" type="dobj"/>
                </token>
                <token content="into" id="18-22"/>
                <token content="the" id="18-23">
                    <pos type="DT"/>
                    <lemma type="the"/>
                </token>
                <token content="back" id="18-24">
                    <pos type="JJ"/>
                    <lemma type="back"/>
                </token>
                <token content="seat" id="18-25">
                    <pos type="NN"/>
                    <lemma type="seat"/>
                    <dep head="18-19" type="prep"/>
                </token>
                <token content="." id="18-26"/>
            </sentence>
            <sentence id="19">
                <token content="Then" id="19-1">
                    <pos type="RB"/>
                    <lemma type="then"/>
                    <dep head="19-4" type="advmod"/>
                </token>
                <token content="my" id="19-2">
                    <pos type="PRP$"/>
                    <lemma type="my"/>
                </token>
                <token content="husband" id="19-3">
                    <pos type="NN"/>
                    <lemma type="husband"/>
                    <dep head="19-4" type="nsubj"/>
                </token>
                <token content="put" id="19-4">
                    <pos type="VBD"/>
                    <lemma type="put"/>
                </token>
                <token content="the" id="19-5">
                    <pos type="DT"/>
                    <lemma type="the"/>
                </token>
                <token content="cart" id="19-6">
                    <pos type="NN"/>
                    <lemma type="cart"/>
                    <dep head="19-4" type="dobj"/>
                </token>
                <token content="in" id="19-7"/>
                <token content="little" id="19-8">
                    <pos type="JJ"/>
                    <lemma type="little"/>
                </token>
                <token content="corral" id="19-9">
                    <pos type="NNS"/>
                    <lemma type="corral"/>
                    <dep head="19-4" type="prep"/>
                </token>
                <token content="in" id="19-10"/>
                <token content="the" id="19-11">
                    <pos type="DT"/>
                    <lemma type="the"/>
                </token>
                <token content="parking" id="19-12">
                    <pos type="NN"/>
                    <lemma type="parking"/>
                </token>
                <token content="lot" id="19-13">
                    <pos type="NN"/>
                    <lemma type="lot"/>
                    <dep head="19-4" type="prep"/>
                </token>
                <token content="that" id="19-14">
                    <pos type="WDT"/>
                    <lemma type="that"/>
                    <dep head="19-15" type="nsubj"/>
                </token>
                <token content="keeps" id="19-15">
                    <pos type="VBZ"/>
                    <lemma type="keep"/>
                </token>
                <token content="the" id="19-16">
                    <pos type="DT"/>
                    <lemma type="the"/>
                </token>
                <token content="carts" id="19-17">
                    <pos type="NNS"/>
                    <lemma type="cart"/>
                    <dep head="19-15" type="dobj"/>
                </token>
                <token content="away" id="19-18"/>
                <token content="from" id="19-19"/>
                <token content="people" id="19-20">
                    <pos type="NNS"/>
                    <lemma type="people"/>
                </token>
                <token content="'s" id="19-21"/>
                <token content="cars" id="19-22">
                    <pos type="NNS"/>
                    <lemma type="car"/>
                    <dep head="19-15" type="prep"/>
                </token>
                <token content="," id="19-23"/>
                <token content="and" id="19-24"/>
                <token content="we" id="19-25">
                    <pos type="PRP"/>
                    <lemma type="we"/>
                    <dep head="19-26" type="nsubj"/>
                </token>
                <token content="got" id="19-26">
                    <pos type="VBD"/>
                    <lemma type="get"/>
                    <dep head="19-4" type="conj"/>
                </token>
                <token content="in" id="19-27"/>
                <token content="our" id="19-28">
                    <pos type="PRP$"/>
                    <lemma type="we"/>
                </token>
                <token content="car" id="19-29">
                    <pos type="NN"/>
                    <lemma type="car"/>
                    <dep head="19-26" type="prep"/>
                </token>
                <token content="and" id="19-30"/>
                <token content="went" id="19-31">
                    <pos type="VBD"/>
                    <lemma type="go"/>
                    <dep head="19-26" type="conj"/>
                </token>
                <token content="home" id="19-32">
                    <pos type="NN"/>
                    <lemma type="home"/>
                    <dep head="19-31" type="dobj"/>
                </token>
                <token content="." id="19-33"/>
            </sentence>
        </sentences>
    </text>
    <annotations>
        <participants>
            <label from="1-1" id="0" name="NPart" text="Sunday" type="participant"/>
            <label from="1-3" id="1" name="ScrPart_shopper" text="my" type="participant"/>
            <label from="1-4" id="2" name="ScrPart_shopper" text="husband" type="participant"/>
            <label from="1-6" id="3" name="ScrPart_shopper" text="I" type="participant"/>
            <label from="1-8" id="4" name="ScrPart_shopper" text="our" type="participant"/>
            <label from="1-9" id="5" name="ScrPart_groceries" text="grocery" type="participant"/>
            <label from="2-1" id="6" name="ScrPart_shopper" text="He" type="participant"/>
            <label from="2-4" id="7" name="ScrPart_grocery_list" text="shopping list" to="2-5" type="participant"/>
            <label from="2-5" id="8" name="ScrPart_grocery_list" text="list" type="participant"/>
            <label from="2-8" id="9" name="ScrPart_shopper" text="his" type="participant"/>
            <label from="2-9" id="10" name="NPart" text="cell phone" to="2-10" type="participant"/>
            <label from="2-10" id="11" name="NPart" text="phone" type="participant"/>
            <label from="3-1" id="12" name="ScrPart_shopper" text="We" type="participant"/>
            <label from="3-5" id="13" name="ScrPart_grocery_shop" text="store" type="participant"/>
            <label from="3-9" id="14" name="NPart" text="afternoon" type="participant"/>
            <label from="3-14" id="15" name="No_label" text="thing" type="participant"/>
            <label from="3-15" id="16" name="ScrPart_shopper" text="we" type="participant"/>
            <label from="3-20" id="17" name="ScrPart_shopping_cart/basket" text="shopping cart" to="3-21" type="participant"/>
            <label from="3-21" id="18" name="ScrPart_shopping_cart/basket" text="cart" type="participant"/>
            <label from="4-1" id="19" name="ScrPart_shopper" text="We" type="participant"/>
            <label from="4-8" id="20" name="ScrPart_section" text="produce area" to="4-9" type="participant"/>
            <label from="4-9" id="21" name="ScrPart_section" text="area" type="participant"/>
            <label from="4-15" id="22" name="ScrPart_groceries" text="fruit" type="participant"/>
            <label from="4-17" id="23" name="ScrPart_groceries" text="vegetables" type="participant"/>
            <label from="5-1" id="24" name="ScrPart_shopper" text="My" type="participant"/>
            <label from="5-2" id="25" name="ScrPart_shopper" text="husband" type="participant"/>
            <label from="5-5" id="26" name="ScrPart_grocery_list" text="list" type="participant"/>
            <label from="6-1" id="27" name="ScrPart_shopper" text="We" type="participant"/>
            <label from="6-4" id="28" name="ScrPart_groceries" text="bananas" type="participant"/>
            <label from="6-7" id="29" name="ScrPart_grocery_list" text="list" type="participant"/>
            <label from="6-10" id="30" name="ScrPart_shopper" text="I" type="participant"/>
            <label from="6-12" id="31" name="ScrPart_shopper" text="we" type="participant"/>
            <label from="6-15" id="32" name="ScrPart_groceries" text="things" type="participant"/>
            <label from="6-17" id="33" name="NPart" text="salad" type="participant"/>
            <label from="6-22" id="34" name="ScrPart_shopper" text="he" type="participant"/>
            <label from="6-25" id="35" name="ScrPart_groceries" text="bananas" type="participant"/>
            <label from="6-27" id="36" name="ScrPart_groceries" text="bell peppers" to="6-28" type="participant"/>
            <label from="6-28" id="37" name="ScrPart_groceries" text="peppers" type="participant"/>
            <label from="6-30" id="38" name="ScrPart_shopper" text="I" type="participant"/>
            <label from="6-32" id="39" name="ScrPart_groceries" text="lettuce" type="participant"/>
            <label from="6-34" id="40" name="ScrPart_groceries" text="radishes" type="participant"/>
            <label from="6-36" id="41" name="ScrPart_groceries" text="tomatoes" type="participant"/>
            <label from="7-2" id="42" name="ScrPart_shopper" text="we" type="participant"/>
            <label from="7-6" id="43" name="ScrPart_section" text="deli area" to="7-7" type="participant"/>
            <label from="7-7" id="44" name="ScrPart_section" text="area" type="participant"/>
            <label from="7-12" id="45" name="ScrPart_groceries" text="turkey" type="participant"/>
            <label from="8-2" id="46" name="ScrPart_grocery_staff" text="man" type="participant"/>
            <label from="8-5" id="47" name="ScrPart_cash_desk" text="counter" type="participant"/>
            <label from="8-8" id="48" name="ScrPart_groceries" text="turkey" type="participant"/>
            <label from="8-10" id="49" name="ScrPart_shopper" text="us" type="participant"/>
            <label from="8-13" id="50" name="ScrPart_groceries" text="it" type="participant"/>
            <label from="8-16" id="51" name="ScrPart_other" text="scale" type="participant"/>
            <label from="8-19" id="52" name="ScrPart_shopper" text="us" type="participant"/>
            <label from="8-21" id="53" name="Unclear" text="amount" type="participant"/>
            <label from="8-22" id="54" name="ScrPart_shopper" text="we" type="participant"/>
            <label from="8-27" id="55" name="ScrPart_groceries" text="it" type="participant"/>
            <label from="8-30" id="56" name="ScrPart_shopper" text="us" type="participant"/>
            <label from="9-2" id="57" name="ScrPart_shopper" text="we" type="participant"/>
            <label from="9-5" id="58" name="ScrPart_section" text="bakery area" to="9-6" type="participant"/>
            <label from="9-6" id="59" name="ScrPart_section" text="area" type="participant"/>
            <label from="9-12" id="60" name="Head_of_Partitive" text="loaf" type="participant"/>
            <label from="9-14" id="61" name="ScrPart_groceries" text="rye bread" to="9-15" type="participant"/>
            <label from="9-15" id="62" name="ScrPart_groceries" text="bread" type="participant"/>
            <label from="9-19" id="63" name="ScrPart_groceries" text="turkey" type="participant"/>
            <label from="10-3" id="64" name="ScrPart_section" text="canned goods area" to="10-5" type="participant"/>
            <label from="10-5" id="65" name="ScrPart_section" text="area" type="participant"/>
            <label from="10-7" id="66" name="ScrPart_shopper" text="we" type="participant"/>
            <label from="10-10" id="67" name="ScrPart_groceries" text="soup" type="participant"/>
            <label from="10-12" id="68" name="ScrPart_groceries" text="white beans" to="10-13" type="participant"/>
            <label from="10-13" id="69" name="ScrPart_groceries" text="beans" type="participant"/>
            <label from="10-16" id="70" name="ScrPart_shopper" text="we" type="participant"/>
            <label from="10-20" id="71" name="ScrPart_section" text="pasta area" to="10-21" type="participant"/>
            <label from="10-21" id="72" name="ScrPart_section" text="area" type="participant"/>
            <label from="10-24" id="73" name="ScrPart_groceries" text="pasta" type="participant"/>
            <label from="10-26" id="74" name="ScrPart_groceries" text="sauce" type="participant"/>
            <label from="11-3" id="75" name="ScrPart_section" text="meat area" to="11-4" type="participant"/>
            <label from="11-4" id="76" name="ScrPart_section" text="area" type="participant"/>
            <label from="11-6" id="77" name="ScrPart_shopper" text="we" type="participant"/>
            <label from="11-10" id="78" name="ScrPart_groceries" text="chicken breasts" to="11-11" type="participant"/>
            <label from="11-11" id="79" name="ScrPart_groceries" text="breasts" type="participant"/>
            <label from="11-14" id="80" name="ScrPart_groceries" text="sausage" type="participant"/>
            <label from="12-2" id="81" name="ScrPart_shopper" text="we" type="participant"/>
            <label from="12-6" id="82" name="ScrPart_section" text="dairy refrigerators" to="12-7" type="participant"/>
            <label from="12-7" id="83" name="ScrPart_section" text="refrigerators" type="participant"/>
            <label from="12-9" id="84" name="ScrPart_shopper" text="we" type="participant"/>
            <label from="12-14" id="85" name="Head_of_Partitive" text="flavors" type="participant"/>
            <label from="12-16" id="86" name="ScrPart_groceries" text="yogurt" type="participant"/>
            <label from="12-17" id="87" name="ScrPart_shopper" text="we" type="participant"/>
            <label from="12-22" id="88" name="ScrPart_groceries" text="milk" type="participant"/>
            <label from="12-24" id="89" name="ScrPart_groceries" text="butter" type="participant"/>
            <label from="12-26" id="90" name="ScrPart_groceries" text="eggs" type="participant"/>
            <label from="13-1" id="91" name="ScrPart_shopper" text="We" type="participant"/>
            <label from="13-7" id="92" name="ScrPart_shopper" text="my" type="participant"/>
            <label from="13-8" id="93" name="ScrPart_shopper" text="husband" type="participant"/>
            <label from="13-11" id="94" name="ScrPart_grocery_list" text="list" type="participant"/>
            <label from="13-14" id="95" name="ScrPart_shopper" text="we" type="participant"/>
            <label from="13-16" id="96" name="ScrPart_shopper" text="we" type="participant"/>
            <label from="13-19" id="97" name="ScrPart_other" text="tin foil" to="13-20" type="participant"/>
            <label from="13-20" id="98" name="ScrPart_other" text="foil" type="participant"/>
            <label from="13-22" id="99" name="ScrPart_other" text="toilet paper" to="13-23" type="participant"/>
            <label from="13-23" id="100" name="ScrPart_other" text="paper" type="participant"/>
            <label from="13-26" id="101" name="ScrPart_shopper" text="we" type="participant"/>
            <label from="13-33" id="102" name="ScrPart_other" text="things" type="participant"/>
            <label from="14-2" id="103" name="ScrPart_shopper" text="we" type="participant"/>
            <label from="14-6" id="104" name="ScrPart_cash_desk" text="check-out" type="participant"/>
            <label from="14-8" id="105" name="ScrPart_shopper" text="we" type="participant"/>
            <label from="14-11" id="106" name="ScrPart_shopper" text="our" type="participant"/>
            <label from="14-12" id="107" name="ScrPart_groceries" text="groceries" type="participant"/>
            <label from="14-15" id="108" name="ScrPart_conveyor_belt" text="conveyor belt" to="14-16" type="participant"/>
            <label from="14-16" id="109" name="ScrPart_conveyor_belt" text="belt" type="participant"/>
            <label from="14-19" id="110" name="ScrPart_grocery_staff" text="clerk" type="participant"/>
            <label from="14-22" id="111" name="ScrPart_groceries" text="item" type="participant"/>
            <label from="14-25" id="112" name="ScrPart_other" text="electronic scanner" to="14-26" type="participant"/>
            <label from="14-26" id="113" name="ScrPart_other" text="scanner" type="participant"/>
            <label from="14-31" id="114" name="ScrPart_groceries" text="it" type="participant"/>
            <label from="15-1" id="115" name="ScrPart_grocery_staff" text="She" type="participant"/>
            <label from="15-3" id="116" name="ScrPart_shopper" text="us" type="participant"/>
            <label from="15-5" id="117" name="ScrPart_price" text="total" type="participant"/>
            <label from="15-8" id="118" name="ScrPart_shopper" text="I" type="participant"/>
            <label from="15-10" id="119" name="ScrPart_shopper" text="my" type="participant"/>
            <label from="15-11" id="120" name="ScrPart_payment_means" text="bank card" to="15-12" type="participant"/>
            <label from="15-12" id="121" name="ScrPart_payment_means" text="card" type="participant"/>
            <label from="15-15" id="122" name="ScrPart_other" text="electronic reader" to="15-16" type="participant"/>
            <label from="15-16" id="123" name="ScrPart_other" text="reader" type="participant"/>
            <label from="16-4" id="124" name="ScrPart_grocery_staff" text="bagger" type="participant"/>
            <label from="16-7" id="125" name="ScrPart_shopper" text="our" type="participant"/>
            <label from="16-8" id="126" name="ScrPart_groceries" text="groceries" type="participant"/>
            <label from="16-11" id="127" name="ScrPart_shopping_bags" text="shopping bags" to="16-12" type="participant"/>
            <label from="16-12" id="128" name="ScrPart_shopping_bags" text="bags" type="participant"/>
            <label from="16-14" id="129" name="ScrPart_shopper" text="we" type="participant"/>
            <label from="16-18" id="130" name="ScrPart_shopper" text="us" type="participant"/>
            <label from="17-1" id="131" name="ScrPart_grocery_staff" text="He" type="participant"/>
            <label from="17-4" id="132" name="ScrPart_shopping_bags" text="bags" type="participant"/>
            <label from="17-8" id="133" name="ScrPart_shopping_cart/basket" text="cart" type="participant"/>
            <label from="18-1" id="134" name="ScrPart_shopper" text="We" type="participant"/>
            <label from="18-4" id="135" name="ScrPart_receipt" text="receipt" type="participant"/>
            <label from="18-7" id="136" name="ScrPart_grocery_staff" text="clerk" type="participant"/>
            <label from="18-11" id="137" name="ScrPart_shopping_cart/basket" text="cart" type="participant"/>
            <label from="18-14" id="138" name="ScrPart_shopper" text="our" type="participant"/>
            <label from="18-15" id="139" name="ScrPart_vehicle" text="car" type="participant"/>
            <label from="18-18" id="140" name="ScrPart_shopper" text="we" type="participant"/>
            <label from="18-21" id="141" name="ScrPart_shopping_bags" text="bags" type="participant"/>
            <label from="18-24" id="142" name="ScrPart_vehicle" text="back seat" to="18-25" type="participant"/>
            <label from="18-25" id="143" name="ScrPart_vehicle" text="seat" type="participant"/>
            <label from="19-2" id="144" name="ScrPart_shopper" text="my" type="participant"/>
            <label from="19-3" id="145" name="ScrPart_shopper" text="husband" type="participant"/>
            <label from="19-6" id="146" name="ScrPart_shopping_cart/basket" text="cart" type="participant"/>
            <label from="19-9" id="147" name="NPart" text="corral" type="participant"/>
            <label from="19-12" id="148" name="NPart" text="parking lot" to="19-13" type="participant"/>
            <label from="19-13" id="149" name="NPart" text="lot" type="participant"/>
            <label from="19-17" id="150" name="ScrPart_shopping_cart/basket" text="carts" type="participant"/>
            <label from="19-20" id="151" name="ScrPart_shopper" text="people" type="participant"/>
            <label from="19-22" id="152" name="ScrPart_vehicle" text="cars" type="participant"/>
            <label from="19-25" id="153" name="ScrPart_shopper" text="we" type="participant"/>
            <label from="19-28" id="154" name="ScrPart_shopper" text="our" type="participant"/>
            <label from="19-29" id="155" name="ScrPart_vehicle" text="car" type="participant"/>
            <label from="19-32" id="156" name="NPart" text="home" type="participant"/>
        </participants>
        <events>
            <label from="1-9" id="157" name="Evoking" text="grocery shopping" to="1-10" type="event"/>
            <label from="1-10" id="158" name="ScrEv_get_groceries" text="shopping" type="event"/>
            <label from="2-6" id="159" name="ScrEv_make_list" text="recorded" type="event"/>
            <label from="3-2" id="160" name="ScrEv_go_grocery" text="arrived" type="event"/>
            <label from="3-18" id="161" name="ScrEv_take_shop_cart" text="get" type="event"/>
            <label from="4-2" id="162" name="ScrEv_enter" text="walked in" to="4-3" type="event"/>
            <label from="4-2" id="163" name="ScrEv_enter" text="walked" type="event"/>
            <label from="4-5" id="164" name="ScrEv_move_section" text="went" type="event"/>
            <label from="4-18" id="165" name="UnrelEv" text="are" type="event"/>
            <label from="5-3" id="166" name="ScrEv_check_list" text="checked" type="event"/>
            <label from="6-3" id="167" name="RelNScrEv" text="had" type="event"/>
            <label from="6-11" id="168" name="UnrelEv" text="said" type="event"/>
            <label from="6-14" id="169" name="ScrEv_get_groceries" text="get" type="event"/>
            <label from="6-23" id="170" name="ScrEv_get_groceries" text="picked out" to="6-24" type="event"/>
            <label from="6-23" id="171" name="ScrEv_get_groceries" text="picked" type="event"/>
            <label from="6-31" id="172" name="ScrEv_get_groceries" text="got" type="event"/>
            <label from="7-3" id="173" name="ScrEv_move_section" text="went" type="event"/>
            <label from="7-9" id="174" name="ScrEv_other" text="ordered" type="event"/>
            <label from="8-6" id="175" name="ScrEv_other" text="sliced" type="event"/>
            <label from="8-12" id="176" name="ScrEv_other" text="measured" type="event"/>
            <label from="8-18" id="177" name="ScrEv_get_groceries" text="give" type="event"/>
            <label from="8-23" id="178" name="UnrelEv" text="wanted" type="event"/>
            <label from="8-26" id="179" name="ScrEv_pack_groceries" text="wrapped" type="event"/>
            <label from="9-3" id="180" name="ScrEv_move_section" text="visited" type="event"/>
            <label from="9-8" id="181" name="ScrEv_get_groceries" text="picked out" to="9-9" type="event"/>
            <label from="9-8" id="182" name="ScrEv_get_groceries" text="picked" type="event"/>
            <label from="9-17" id="183" name="UnrelEv" text="put" type="event"/>
            <label from="10-3" id="184" name="UnrelEv" text="canned" type="event"/>
            <label from="10-8" id="185" name="ScrEv_get_groceries" text="picked out" to="10-9" type="event"/>
            <label from="10-8" id="186" name="ScrEv_get_groceries" text="picked" type="event"/>
            <label from="10-17" id="187" name="ScrEv_move_section" text="went" type="event"/>
            <label from="10-23" id="188" name="ScrEv_get_groceries" text="get" type="event"/>
            <label from="11-7" id="189" name="ScrEv_get_groceries" text="picked up" to="11-8" type="event"/>
            <label from="11-7" id="190" name="ScrEv_get_groceries" text="picked" type="event"/>
            <label from="12-3" id="191" name="ScrEv_move_section" text="went" type="event"/>
            <label from="12-11" id="192" name="ScrEv_get_groceries" text="picked out" to="12-12" type="event"/>
            <label from="12-11" id="193" name="ScrEv_get_groceries" text="picked" type="event"/>
            <label from="12-18" id="194" name="UnrelEv" text="like" type="event"/>
            <label from="12-21" id="195" name="ScrEv_get_groceries" text="got" type="event"/>
            <label from="13-4" id="196" name="UnrelEv" text="done" type="event"/>
            <label from="13-9" id="197" name="ScrEv_check_list" text="checked" type="event"/>
            <label from="13-18" id="198" name="UnrelEv" text="forgotten" type="event"/>
            <label from="13-27" id="199" name="ScrEv_move_section" text="went back" to="13-28" type="event"/>
            <label from="13-27" id="200" name="ScrEv_move_section" text="went" type="event"/>
            <label from="13-30" id="201" name="ScrEv_get_groceries" text="got" type="event"/>
            <label from="14-3" id="202" name="ScrEv_go_checkout" text="went" type="event"/>
            <label from="14-9" id="203" name="ScrEv_put_conveyor" text="put" type="event"/>
            <label from="14-20" id="204" name="ScrEv_cashier_scan/weight" text="scanned" type="event"/>
            <label from="14-28" id="205" name="ScrEv_cashier_scan/weight" text="find out" to="14-29" type="event"/>
            <label from="14-28" id="206" name="ScrEv_cashier_scan/weight" text="find" type="event"/>
            <label from="14-32" id="207" name="RelNScrEv" text="cost" type="event"/>
            <label from="15-2" id="208" name="UnrelEv" text="told" type="event"/>
            <label from="15-9" id="209" name="ScrEv_pay" text="swiped" type="event"/>
            <label from="15-18" id="210" name="ScrEv_pay" text="pay" type="event"/>
            <label from="16-6" id="211" name="ScrEv_pack_groceries" text="putting" type="event"/>
            <label from="16-16" id="212" name="ScrEv_take_bags" text="brought" type="event"/>
            <label from="17-2" id="213" name="ScrEv_other" text="put" type="event"/>
            <label from="18-2" id="214" name="ScrEv_get_receipt" text="got" type="event"/>
            <label from="18-9" id="215" name="ScrEv_bring_vehicle" text="pushed" type="event"/>
            <label from="18-19" id="216" name="ScrEv_bring_vehicle" text="moved" type="event"/>
            <label from="19-4" id="217" name="ScrEv_return_shop_cart" text="put" type="event"/>
            <label from="19-15" id="218" name="UnrelEv" text="keeps" type="event"/>
            <label from="19-26" id="219" name="ScrEv_leave" text="got in" to="19-27" type="event"/>
            <label from="19-26" id="220" name="ScrEv_leave" text="got" type="event"/>
            <label from="19-31" id="221" name="ScrEv_leave" text="went" type="event"/>
        </events>
        <chains>
            <chain elements="1 3 24 30 38 92 118 119 144"/>
            <chain elements="2 4 3" name="group_I_husband"/>
            <chain elements="2 6 9 25 34 93 145"/>
            <chain elements="4 12 16 19 27 31 42 49 52 54 56 57 66 70 77 81 84 87 91 95 96 101 103 105 106 116 125 129 130 134 138 140 153 154"/>
            <chain elements="8 26 29 94"/>
            <chain elements="28 35"/>
            <chain elements="45 48 50 55 63"/>
            <chain elements="98 102 100" name="group_foil_paper"/>
            <chain elements="111 114"/>
            <chain elements="110 115 136"/>
            <chain elements="124 131"/>
            <chain elements="128 132"/>
            <chain elements="18 133 137 146"/>
            <chain elements="139 155"/>
        </chains>
    </annotations>
</story>
